soed/__init__.py
soed-1.0.10.dist-info/LICENSE
soed-1.0.10.dist-info/METADATA
soed-1.0.10.dist-info/WHEEL
soed-1.0.10.dist-info/top_level.txt
soed-1.0.10.dist-info/RECORD
