Metadata-Version: 2.1
Name: soed
Version: 1.0.10
Summary: Self Organizing Error Driven Artificial Neural Network
Home-page: https://github.com/royjafari/SOED
Author: Roy Jafari
Author-email: royxjafari@gmail.com
Maintainer: Jason Jafari
Maintainer-email: me@jasonjafari.com
Project-URL: Documentation, https://github.com/royjafari/SOED/blob/main/README.md
Project-URL: Source, https://github.com/royjafari/SOED
Project-URL: Tracker, https://github.com/royjafari/SOED/issues
Keywords: machine learning AI Artificial Neural Network
Classifier: Development Status :: 5 - Production/Stable
Classifier: Intended Audience :: Developers
Classifier: Intended Audience :: Science/Research
Classifier: Topic :: Software Development :: Libraries :: Python Modules
Classifier: Topic :: Scientific/Engineering :: Artificial Intelligence
Classifier: License :: OSI Approved :: MIT License
Classifier: Programming Language :: Python :: 3.12
License-File: LICENSE
Requires-Dist: numpy==2.2.1
Requires-Dist: pandas==2.2.3
Requires-Dist: scikit-learn==1.6.0
Requires-Dist: MiniSom==2.3.3
Requires-Dist: scipy==1.14.1
Requires-Dist: python-dateutil==2.9.0.post0
Requires-Dist: six==1.17.0
Requires-Dist: threadpoolctl==3.5.0
Requires-Dist: tzdata==2024.2
